github_app_access_token_fetcher/__init__.py
github_app_access_token_fetcher-1.0.1.dist-info/entry_points.txt
github_app_access_token_fetcher-1.0.1.dist-info/WHEEL
github_app_access_token_fetcher-1.0.1.dist-info/METADATA
github_app_access_token_fetcher-1.0.1.dist-info/RECORD
